dateparser/__init__.py
dateparser/conf.py
dateparser/date.py
dateparser/date_parser.py
dateparser/freshness_date_parser.py
dateparser/parser.py
dateparser/timezone_parser.py
dateparser/timezones.py
dateparser/calendars/__init__.py
dateparser/calendars/hijri.py
dateparser/calendars/hijri_parser.py
dateparser/calendars/jalali.py
dateparser/calendars/jalali_parser.py
dateparser/custom_language_detection/__init__.py
dateparser/custom_language_detection/fasttext.py
dateparser/custom_language_detection/langdetect.py
dateparser/custom_language_detection/language_mapping.py
dateparser/data/__init__.py
dateparser/data/languages_info.py
dateparser/data/date_translation_data/__init__.py
dateparser/data/date_translation_data/af.py
dateparser/data/date_translation_data/agq.py
dateparser/data/date_translation_data/ak.py
dateparser/data/date_translation_data/am.py
dateparser/data/date_translation_data/ar.py
dateparser/data/date_translation_data/as.py
dateparser/data/date_translation_data/asa.py
dateparser/data/date_translation_data/ast.py
dateparser/data/date_translation_data/az-Cyrl.py
dateparser/data/date_translation_data/az-Latn.py
dateparser/data/date_translation_data/az.py
dateparser/data/date_translation_data/bas.py
dateparser/data/date_translation_data/be.py
dateparser/data/date_translation_data/bem.py
dateparser/data/date_translation_data/bez.py
dateparser/data/date_translation_data/bg.py
dateparser/data/date_translation_data/bm.py
dateparser/data/date_translation_data/bn.py
dateparser/data/date_translation_data/bo.py
dateparser/data/date_translation_data/br.py
dateparser/data/date_translation_data/brx.py
dateparser/data/date_translation_data/bs-Cyrl.py
dateparser/data/date_translation_data/bs-Latn.py
dateparser/data/date_translation_data/bs.py
dateparser/data/date_translation_data/ca.py
dateparser/data/date_translation_data/ce.py
dateparser/data/date_translation_data/cgg.py
dateparser/data/date_translation_data/chr.py
dateparser/data/date_translation_data/ckb.py
dateparser-1.1.8.dist-info/AUTHORS.rst
dateparser-1.1.8.dist-info/LICENSE
dateparser-1.1.8.dist-info/METADATA
dateparser-1.1.8.dist-info/WHEEL
dateparser-1.1.8.dist-info/entry_points.txt
dateparser-1.1.8.dist-info/top_level.txt
dateparser-1.1.8.dist-info/RECORD
