Metadata-Version: 2.1
Name: dateparser
Version: 1.1.8
Summary: Date parsing library designed to parse dates from HTML pages
Home-page: https://github.com/scrapinghub/dateparser
Author: Scrapinghub
Author-email: opensource@zyte.com
License: BSD
Project-URL: History, https://dateparser.readthedocs.io/en/latest/history.html
Keywords: dateparser
Classifier: Development Status :: 5 - Production/Stable
Classifier: Intended Audience :: Developers
Classifier: License :: OSI Approved :: BSD License
Classifier: Natural Language :: English
Classifier: Programming Language :: Python :: 3
Classifier: Programming Language :: Python :: 3.7
Classifier: Programming Language :: Python :: 3.8
Classifier: Programming Language :: Python :: 3.9
Classifier: Programming Language :: Python :: 3.10
Classifier: Programming Language :: Python :: 3.11
Classifier: Programming Language :: Python :: Implementation :: CPython
Requires-Python: >=3.7
Provides-Extra: calendars
Provides-Extra: fasttext
Provides-Extra: langdetect
License-File: LICENSE
License-File: AUTHORS.rst
